example_publish_pypi_medium/__init__.py
example_publish_pypi_medium/example/__init__.py
example_publish_pypi_medium/example/custom_sklearn.py
finra_canary-5.8.2.dist-info/METADATA
finra_canary-5.8.2.dist-info/WHEEL
finra_canary-5.8.2.dist-info/top_level.txt
finra_canary-5.8.2.dist-info/RECORD
