Metadata-Version: 2.1
Name: finra-canary
Version: 5.8.2
Home-page: https://github.com/gmyrianthous/example-publish-pypi
Author: Shubham_fnra
Author-email: shubham.agrawal@finra.org
License: MIT
Keywords: ceedee project
Requires-Dist: scikit-learn
Requires-Dist: requests
